{
  "author":"Buildfire"
,"pluginName":"Vimeo"
,"pluginDescription":"Sync your Vimeo channel, user feed, or MP4 stream to provide a fresh viewing experience. New videos automatically update in your app for seamless content delivery."
,"supportEmail":"support@buildfire.com"
,"supportSite":"http://learn.appdocumentation.com/plugin-tutorials/vimeo-plugin-tutorial/"
,"offlineModeEnabled": true
,"control":{
  "content":{
    "enabled":true
  }
, "design":{
    "enabled":true
  }
, "settings":{
    "enabled":false
  }
}
,"widget":{

},
  "features" : [{"name" : "sharing"}],
  "languages" : ["en"]
}
